ctoken/__init__.py
ctoken/calculation.py
ctoken/pricing_data.py
ctoken/response_parser.py
ctoken/token_estimator.py
ctoken/data/__init__.py
ctoken/data/pricing_data.py
ctoken-1.0.5.dist-info/licenses/LICENSE
ctoken-1.0.5.dist-info/METADATA
ctoken-1.0.5.dist-info/WHEEL
ctoken-1.0.5.dist-info/top_level.txt
ctoken-1.0.5.dist-info/RECORD
