Metadata-Version: 2.4
Name: ctoken
Version: 1.0.5
Summary: A lightweight library to count and estimate costs for OpenAI API tokens
Home-page: https://github.com/o1x3/ctoken
Author: Karthik Vinayan
Author-email: Karthik Vinayan <karthik@o1x3.com>
License-Expression: MIT
Project-URL: Homepage, https://github.com/o1x3/ctoken
Project-URL: Repository, https://github.com/o1x3/ctoken
Project-URL: Issues, https://github.com/o1x3/ctoken/issues
Classifier: Programming Language :: Python :: 3
Classifier: Operating System :: OS Independent
Classifier: Intended Audience :: Developers
Classifier: Topic :: Software Development :: Libraries :: Python Modules
Classifier: Topic :: Text Processing :: Linguistic
Requires-Python: >=3.8
License-File: LICENSE
Requires-Dist: requests>=2.25.0
Dynamic: author
Dynamic: classifier
Dynamic: home-page
Dynamic: license-file
Dynamic: requires-dist
Dynamic: requires-python
